easy_profile/__init__.py
easy_profile/middleware.py
easy_profile/profiler.py
easy_profile/reporters.py
easy_profile/termcolors.py
sqlalchemy_easy_profile-1.3.0.dist-info/LICENSE
sqlalchemy_easy_profile-1.3.0.dist-info/METADATA
sqlalchemy_easy_profile-1.3.0.dist-info/WHEEL
sqlalchemy_easy_profile-1.3.0.dist-info/top_level.txt
sqlalchemy_easy_profile-1.3.0.dist-info/RECORD
