Metadata-Version: 2.1
Name: sqlalchemy-easy-profile
Version: 1.3.0
Summary: An easy profiler for SQLAlchemy queries
Home-page: https://github.com/dmvass/sqlalchemy-easy-profile
Author: Dmitri Vasilishin
Author-email: vasilishin.d.o@gmail.com
Keywords: sqlalchemy,easy,profile,profiler,profiling
Classifier: Development Status :: 5 - Production/Stable
Classifier: Intended Audience :: Developers
Classifier: Programming Language :: Python :: 3
Classifier: Programming Language :: Python :: 3.7
Classifier: Programming Language :: Python :: 3.8
Classifier: Programming Language :: Python :: 3.9
Classifier: License :: OSI Approved :: MIT License
Classifier: Operating System :: OS Independent
License-File: LICENSE
Requires-Dist: sqlalchemy (<2.1)
Requires-Dist: sqlparse (>=0.3.0)
Provides-Extra: dev
Requires-Dist: tox ; extra == 'dev'
